plone.namedfile-7.2.1-py3.13-nspkg.pth
plone/namedfile/__init__.py
plone/namedfile/adapters.py
plone/namedfile/browser.py
plone/namedfile/configure.zcml
plone/namedfile/copy.py
plone/namedfile/editor.py
plone/namedfile/editor.zcml
plone/namedfile/field.py
plone/namedfile/field.zcml
plone/namedfile/file.py
plone/namedfile/handler.py
plone/namedfile/handler.rst
plone/namedfile/handler.zcml
plone/namedfile/interfaces.py
plone/namedfile/marshaler.py
plone/namedfile/marshaler.rst
plone/namedfile/marshaler.zcml
plone/namedfile/picture.py
plone/namedfile/scaling.py
plone/namedfile/scaling.zcml
plone/namedfile/storages.py
plone/namedfile/test.pt
plone/namedfile/testing.py
plone/namedfile/testing.zcml
plone/namedfile/usage.rst
plone/namedfile/utils.rst
plone/namedfile/z3c-blobfile.zcml
plone/namedfile/tests/900.jpg
plone/namedfile/tests/900.webp
plone/namedfile/tests/__init__.py
plone/namedfile/tests/dummy.py
plone/namedfile/tests/file.pdf
plone/namedfile/tests/image.bmp
plone/namedfile/tests/image.gif
plone/namedfile/tests/image.jpg
plone/namedfile/tests/image.png
plone/namedfile/tests/image.svg
plone/namedfile/tests/image.tif
plone/namedfile/tests/image_large_header.svg
plone/namedfile/tests/image_loseless.webp
plone/namedfile/tests/image_lossy.webp
plone/namedfile/tests/notimage.doc
plone/namedfile/tests/test_adapters.py
plone/namedfile/tests/test_blobfile.py
plone/namedfile/tests/test_display_file.py
plone/namedfile/tests/test_doctests.py
plone/namedfile/tests/test_image.py
plone/namedfile/tests/test_scaling.py
plone/namedfile/tests/test_scaling_functional.py
plone/namedfile/tests/test_storable.py
plone/namedfile/tests/test_svg.py
plone/namedfile/tests/test_utils.py
plone/namedfile/tests/test_validation.py
plone/namedfile/tests/tool.gif
plone/namedfile/utils/__init__.py
plone/namedfile/utils/jpeg_utils.py
plone/namedfile/utils/png_utils.py
plone/namedfile/utils/svg_utils.py
plone_namedfile-7.2.1.dist-info/METADATA
plone_namedfile-7.2.1.dist-info/WHEEL
plone_namedfile-7.2.1.dist-info/namespace_packages.txt
plone_namedfile-7.2.1.dist-info/top_level.txt
plone_namedfile-7.2.1.dist-info/RECORD
