Metadata-Version: 2.4
Name: plone.namedfile
Version: 7.2.1
Summary: File types and fields for images, files and blob files with filenames
Home-page: https://pypi.org/project/plone.namedfile
Author: Laurence Rowe, Martin Aspeli
Author-email: plone-developers@lists.sourceforge.net
License: BSD
Keywords: plone named file image blob
Classifier: Development Status :: 5 - Production/Stable
Classifier: Framework :: Plone
Classifier: Framework :: Plone :: 6.0
Classifier: Framework :: Plone :: 6.1
Classifier: Framework :: Plone :: Core
Classifier: Programming Language :: Python
Classifier: Programming Language :: Python :: 3.9
Classifier: Programming Language :: Python :: 3.10
Classifier: Programming Language :: Python :: 3.11
Classifier: Programming Language :: Python :: 3.12
Classifier: Programming Language :: Python :: 3.13
Classifier: Topic :: Software Development :: Libraries :: Python Modules
Classifier: License :: OSI Approved :: BSD License
Requires-Python: >=3.9
Requires-Dist: BeautifulSoup4
Requires-Dist: persistent
Requires-Dist: piexif
Requires-Dist: Pillow
Requires-Dist: plone.app.uuid>=2.2.0
Requires-Dist: plone.base
Requires-Dist: plone.dexterity
Requires-Dist: plone.memoize
Requires-Dist: plone.protect
Requires-Dist: plone.rfc822>=2.0.0
Requires-Dist: plone.scale[storage]>=4.2.0
Requires-Dist: plone.schemaeditor
Requires-Dist: plone.supermodel
Requires-Dist: Products.CMFCore
Requires-Dist: setuptools
Requires-Dist: z3c.caching
Requires-Dist: zope.cachedescriptors
Requires-Dist: zope.copy
Requires-Dist: Zope
Provides-Extra: test
Requires-Dist: lxml; extra == "test"
Requires-Dist: plone.app.testing; extra == "test"
Requires-Dist: plone.testing; extra == "test"
Dynamic: author
Dynamic: author-email
Dynamic: classifier
Dynamic: description
Dynamic: home-page
Dynamic: keywords
Dynamic: license
Dynamic: provides-extra
Dynamic: requires-dist
Dynamic: requires-python
Dynamic: summary
